CHANGELOG.txt
LICENCE.txt
MANIFEST.in
README.txt
setup.py
Dev_WordList_Gen/__init__.py
Dev_WordList_Gen.egg-info/PKG-INFO
Dev_WordList_Gen.egg-info/SOURCES.txt
Dev_WordList_Gen.egg-info/dependency_links.txt
Dev_WordList_Gen.egg-info/top_level.txt