Metadata-Version: 2.1
Name: Dev-WordList-Gen
Version: 0.0.3
Summary: Create a Wordlist Easily.
Home-page: UNKNOWN
Author: Logendher Gunasekaran
Author-email: logendher@bytfort.com
License: MIT
Keywords: wordlist
Platform: UNKNOWN
Classifier: Development Status :: 5 - Production/Stable
Classifier: Intended Audience :: Education
Classifier: Operating System :: Microsoft :: Windows :: Windows 10
Classifier: License :: OSI Approved :: MIT License
Classifier: Programming Language :: Python :: 3
License-File: LICENCE.txt
